jupyterlite_pyodide_lock/__init__.py
jupyterlite_pyodide_lock/app.py
jupyterlite_pyodide_lock/constants.py
jupyterlite_pyodide_lock/py.typed
jupyterlite_pyodide_lock/utils.py
jupyterlite_pyodide_lock/addons/__init__.py
jupyterlite_pyodide_lock/addons/_base.py
jupyterlite_pyodide_lock/addons/lock.py
jupyterlite_pyodide_lock/addons/offline.py
jupyterlite_pyodide_lock/lockers/__init__.py
jupyterlite_pyodide_lock/lockers/_base.py
jupyterlite_pyodide_lock/lockers/browser.py
jupyterlite_pyodide_lock/lockers/tornado.py
jupyterlite_pyodide_lock/lockers/handlers/__init__.py
jupyterlite_pyodide_lock/lockers/handlers/cacher.py
jupyterlite_pyodide_lock/lockers/handlers/freezer.py
jupyterlite_pyodide_lock/lockers/handlers/lock.html.j2
jupyterlite_pyodide_lock/lockers/handlers/logger.py
jupyterlite_pyodide_lock/lockers/handlers/mime.py
jupyterlite_pyodide_lock/lockers/handlers/solver.py
jupyterlite_pyodide_lock-0.1.1.dist-info/entry_points.txt
jupyterlite_pyodide_lock-0.1.1.dist-info/LICENSE
jupyterlite_pyodide_lock-0.1.1.dist-info/WHEEL
jupyterlite_pyodide_lock-0.1.1.dist-info/METADATA
jupyterlite_pyodide_lock-0.1.1.dist-info/RECORD
