Metadata-Version: 2.3
Name: jupyterlite-pyodide-lock
Version: 0.1.1
Summary: Create pre-solved environments for jupyterlite-pyodide-kernel with pyodide-lock
Author: jupyterlite-pyodide-lock contributors
Requires-Python: >=3.10
Classifier: Framework :: Jupyter
Classifier: Framework :: Jupyter :: JupyterLab
Classifier: Framework :: Jupyter :: JupyterLab :: 4
Classifier: License :: OSI Approved :: BSD License
Classifier: Programming Language :: Python
Classifier: Programming Language :: Python :: 3
Classifier: Programming Language :: Python :: 3.10
Classifier: Programming Language :: Python :: 3.11
Classifier: Programming Language :: Python :: 3.12
Classifier: Programming Language :: Python :: 3.13
Classifier: Typing :: Typed
Requires-Dist: jupyterlite-core >=0.3.0,<0.6.0
Requires-Dist: jupyterlite-pyodide-kernel >=0.3.1,<0.6.0 ; platform_machine != "wasm32"
Requires-Dist: pyodide-lock[wheel] >=0.1.0a4,<0.2.0
Requires-Dist: tornado >=6.1.0 ; platform_machine != "wasm32"
Requires-Dist: psutil >=6
Requires-Dist: pytest >=8,<9 ; extra == "test"
Requires-Dist: pytest-cov ; extra == "test"
Requires-Dist: pytest-html ; extra == "test"
Project-URL: Bug Tracker, https://github.com/deathbeds/jupyterlite-pyodide-lock/issues
Project-URL: Changelog, https://github.com/deathbeds/jupyterlite-pyodide-lock/blob/main/CHANGELOG.md
Project-URL: Documentation, https://jupyterlite-pyodide-lock.rtfd.org
Project-URL: PyPI, https://pypi.org/project/jupyterlite-pyodide-lock
Project-URL: Source, https://github.com/deathbeds/jupyterlite-pyodide-lock/tree/main
Provides-Extra: test
